DataShine/DataShine.py
DataShine/__init__.py
DataShine-2.0.2.dist-info/LICENSE
DataShine-2.0.2.dist-info/METADATA
DataShine-2.0.2.dist-info/WHEEL
DataShine-2.0.2.dist-info/top_level.txt
DataShine-2.0.2.dist-info/RECORD
